odoo/addons/web_ir_actions_act_multi/README.rst
odoo/addons/web_ir_actions_act_multi/__init__.py
odoo/addons/web_ir_actions_act_multi/__manifest__.py
odoo/addons/web_ir_actions_act_multi/i18n/web_ir_actions_act_multi.pot
odoo/addons/web_ir_actions_act_multi/static/description/icon.png
odoo/addons/web_ir_actions_act_multi/static/src/js/web_ir_actions_act_multi.js
odoo/addons/web_ir_actions_act_multi/views/web_ir_actions_act_multi.xml
odoo11_addon_web_ir_actions_act_multi-11.0.1.0.1.dist-info/METADATA
odoo11_addon_web_ir_actions_act_multi-11.0.1.0.1.dist-info/WHEEL
odoo11_addon_web_ir_actions_act_multi-11.0.1.0.1.dist-info/top_level.txt
odoo11_addon_web_ir_actions_act_multi-11.0.1.0.1.dist-info/RECORD
